README.md
setup.py
FinMind/__init__.py
FinMind/_version.py
FinMind/config.py
FinMind/BackTestSystem/BaseClass.py
FinMind/BackTestSystem/__init__.py
FinMind/BackTestSystem/utils.py
FinMind/BackTestSystem/Strategies/Bias.py
FinMind/BackTestSystem/Strategies/ContinueHolding.py
FinMind/BackTestSystem/Strategies/InstitutionalInvestorsFollower.py
FinMind/BackTestSystem/Strategies/Kd.py
FinMind/BackTestSystem/Strategies/KdCrossOver.py
FinMind/BackTestSystem/Strategies/MaCrossOver.py
FinMind/BackTestSystem/Strategies/MacdCrossOver.py
FinMind/BackTestSystem/Strategies/MaxMinPeriodBias.py
FinMind/BackTestSystem/Strategies/NaiveKd.py
FinMind/BackTestSystem/Strategies/ShortSaleMarginPurchaseRatio.py
FinMind/BackTestSystem/Strategies/__init__.py
FinMind/Crawler/BasedClass.py
FinMind/Crawler/GovernmentBonds.py
FinMind/Crawler/RawMaterialFuturesPrices.py
FinMind/Crawler/__init__.py
FinMind/Crawler/demo.py
FinMind/Data/Load.py
FinMind/Data/__init__.py
FinMind/Schema/__init__.py
FinMind/Schema/output.py
test_F.egg-info/PKG-INFO
test_F.egg-info/SOURCES.txt
test_F.egg-info/dependency_links.txt
test_F.egg-info/requires.txt
test_F.egg-info/top_level.txt