Metadata-Version: 2.1
Name: test-F
Version: 1.1.11
Summary: financial mining
Home-page: https://github.com/linsamtw
Author: linsam
Author-email: samlin266118@gmail.com
License: UNKNOWN
Project-URL: documentation, https://linsamtw.github.io/FinMindDoc/
Project-URL: Source, https://github.com/linsamtw/FinMind
Keywords: financial,python
Platform: UNKNOWN
Classifier: Development Status :: 3 - Alpha
